setup.cfg
setup.py
gaussian_dstrbtn/Binomialdistribution.py
gaussian_dstrbtn/Gaussiandistribution.py
gaussian_dstrbtn/Generaldistribution.py
gaussian_dstrbtn/__init__.py
gaussian_dstrbtn.egg-info/PKG-INFO
gaussian_dstrbtn.egg-info/SOURCES.txt
gaussian_dstrbtn.egg-info/dependency_links.txt
gaussian_dstrbtn.egg-info/not-zip-safe
gaussian_dstrbtn.egg-info/top_level.txt